{
  "run_at_kst": "2026-06-09T23:30:14.487232+09:00",
  "sources": {
    "a_stocks": "AkShare (Eastmoney via 中国证监会)",
    "hk_us_kr": "Yahoo Finance (yfinance)"
  },
  "watchlist": [
    {
      "id": "600519",
      "name": "귀주모태주",
      "ex": "상해",
      "sector": "백주",
      "type": "a_stock",
      "price": 1256.0,
      "change_pct": -0.55,
      "prev_close": 1263.0,
      "currency": "CNY",
      "source": "yfinance",
      "delay": "15~20min",
      "found": true
    },
    {
      "id": "601318",
      "name": "중국평안",
      "ex": "상해",
      "sector": "보험",
      "type": "a_stock",
      "price": 53.93,
      "change_pct": 1.03,
      "prev_close": 53.38,
      "currency": "CNY",
      "source": "yfinance",
      "delay": "15~20min",
      "found": true
    },
    {
      "id": "300750",
      "name": "CATL",
      "ex": "심천",
      "sector": "배터리",
      "type": "a_stock",
      "price": 399.5,
      "change_pct": 1.59,
      "prev_close": 393.25,
      "currency": "CNY",
      "source": "yfinance",
      "delay": "15~20min",
      "found": true
    },
    {
      "id": "601398",
      "name": "공상은행",
      "ex": "상해",
      "sector": "금융",
      "type": "a_stock",
      "price": 7.54,
      "change_pct": 0.53,
      "prev_close": 7.5,
      "currency": "CNY",
      "source": "yfinance",
      "delay": "15~20min",
      "found": true
    },
    {
      "id": "601288",
      "name": "농업은행",
      "ex": "상해",
      "sector": "금융",
      "type": "a_stock",
      "price": 6.6,
      "change_pct": 0.46,
      "prev_close": 6.57,
      "currency": "CNY",
      "source": "yfinance",
      "delay": "15~20min",
      "found": true
    },
    {
      "id": "601857",
      "name": "중국석유",
      "ex": "상해",
      "sector": "에너지",
      "type": "a_stock",
      "price": 10.34,
      "change_pct": -5.57,
      "prev_close": 10.95,
      "currency": "CNY",
      "source": "yfinance",
      "delay": "15~20min",
      "found": true
    },
    {
      "id": "600036",
      "name": "초상은행",
      "ex": "상해",
      "sector": "금융",
      "type": "a_stock",
      "price": 38.49,
      "change_pct": -0.03,
      "prev_close": 38.5,
      "currency": "CNY",
      "source": "yfinance",
      "delay": "15~20min",
      "found": true
    },
    {
      "id": "601628",
      "name": "중국인수",
      "ex": "상해",
      "sector": "보험",
      "type": "a_stock",
      "price": 33.14,
      "change_pct": 0.42,
      "prev_close": 33.0,
      "currency": "CNY",
      "source": "yfinance",
      "delay": "15~20min",
      "found": true
    },
    {
      "id": "600028",
      "name": "시노펙",
      "ex": "상해",
      "sector": "에너지",
      "type": "a_stock",
      "price": 4.79,
      "change_pct": -2.44,
      "prev_close": 4.91,
      "currency": "CNY",
      "source": "yfinance",
      "delay": "15~20min",
      "found": true
    },
    {
      "id": "601988",
      "name": "중국은행",
      "ex": "상해",
      "sector": "금융",
      "type": "a_stock",
      "price": 6.13,
      "change_pct": -0.16,
      "prev_close": 6.14,
      "currency": "CNY",
      "source": "yfinance",
      "delay": "15~20min",
      "found": true
    },
    {
      "id": "000858",
      "name": "우량예",
      "ex": "심천",
      "sector": "백주",
      "type": "a_stock",
      "price": 79.11,
      "change_pct": -1.08,
      "prev_close": 79.97,
      "currency": "CNY",
      "source": "yfinance",
      "delay": "15~20min",
      "found": true
    },
    {
      "id": "600276",
      "name": "형서의약",
      "ex": "상해",
      "sector": "의약",
      "type": "a_stock",
      "price": 46.38,
      "change_pct": 0.96,
      "prev_close": 45.94,
      "currency": "CNY",
      "source": "yfinance",
      "delay": "15~20min",
      "found": true
    },
    {
      "id": "000333",
      "name": "메이디",
      "ex": "심천",
      "sector": "가전",
      "type": "a_stock",
      "price": 82.36,
      "change_pct": -0.44,
      "prev_close": 82.72,
      "currency": "CNY",
      "source": "yfinance",
      "delay": "15~20min",
      "found": true
    },
    {
      "id": "600009",
      "name": "상해공항",
      "ex": "상해",
      "sector": "인프라",
      "type": "a_stock",
      "price": 23.72,
      "change_pct": 3.13,
      "prev_close": 23.0,
      "currency": "CNY",
      "source": "yfinance",
      "delay": "15~20min",
      "found": true
    },
    {
      "id": "600030",
      "name": "CITIC증권",
      "ex": "상해",
      "sector": "증권",
      "type": "a_stock",
      "price": 25.52,
      "change_pct": 0.35,
      "prev_close": 25.43,
      "currency": "CNY",
      "source": "yfinance",
      "delay": "15~20min",
      "found": true
    },
    {
      "id": "0700.HK",
      "name": "텐센트",
      "ex": "홍콩",
      "sector": "IT",
      "type": "hk_stock",
      "price": 453.2,
      "prev_close": 446.4,
      "change_pct": 1.52,
      "currency": "HKD",
      "found": true
    },
    {
      "id": "9988.HK",
      "name": "알리바바",
      "ex": "홍콩",
      "sector": "전자상거래",
      "type": "hk_stock",
      "price": 117.1,
      "prev_close": 118.8,
      "change_pct": -1.43,
      "currency": "HKD",
      "found": true
    },
    {
      "id": "9618.HK",
      "name": "징둥",
      "ex": "홍콩",
      "sector": "전자상거래",
      "type": "hk_stock",
      "price": 114.0,
      "prev_close": 113.5,
      "change_pct": 0.44,
      "currency": "HKD",
      "found": true
    },
    {
      "id": "0939.HK",
      "name": "건설은행",
      "ex": "홍콩",
      "sector": "금융",
      "type": "hk_stock",
      "price": 8.69,
      "prev_close": 8.76,
      "change_pct": -0.8,
      "currency": "HKD",
      "found": true
    },
    {
      "id": "1398.HK",
      "name": "공상은행H",
      "ex": "홍콩",
      "sector": "금융",
      "type": "hk_stock",
      "price": 6.93,
      "prev_close": 6.93,
      "change_pct": 0.0,
      "currency": "HKD",
      "found": true
    },
    {
      "id": "0941.HK",
      "name": "차이나모바일",
      "ex": "홍콩",
      "sector": "통신",
      "type": "hk_stock",
      "price": 82.3,
      "prev_close": 82.4,
      "change_pct": -0.12,
      "currency": "HKD",
      "found": true
    },
    {
      "id": "1288.HK",
      "name": "농업은행H",
      "ex": "홍콩",
      "sector": "금융",
      "type": "hk_stock",
      "price": 5.73,
      "prev_close": 5.82,
      "change_pct": -1.55,
      "currency": "HKD",
      "found": true
    },
    {
      "id": "0883.HK",
      "name": "CNOOC",
      "ex": "홍콩",
      "sector": "에너지",
      "type": "hk_stock",
      "price": 26.7,
      "prev_close": 27.06,
      "change_pct": -1.33,
      "currency": "HKD",
      "found": true
    },
    {
      "id": "3690.HK",
      "name": "메이투안",
      "ex": "홍콩",
      "sector": "인터넷",
      "type": "hk_stock",
      "price": 77.2,
      "prev_close": 76.25,
      "change_pct": 1.25,
      "currency": "HKD",
      "found": true
    },
    {
      "id": "1810.HK",
      "name": "샤오미",
      "ex": "홍콩",
      "sector": "IT",
      "type": "hk_stock",
      "price": 27.2,
      "prev_close": 27.38,
      "change_pct": -0.66,
      "currency": "HKD",
      "found": true
    },
    {
      "id": "BABA",
      "name": "알리바바ADR",
      "ex": "NYSE",
      "sector": "전자상거래",
      "type": "us_adr",
      "price": 121.06,
      "prev_close": 119.92,
      "change_pct": 0.95,
      "currency": "USD",
      "found": true
    },
    {
      "id": "PDD",
      "name": "핀둬둬",
      "ex": "NASDAQ",
      "sector": "전자상거래",
      "type": "us_adr",
      "price": 82.7,
      "prev_close": 82.83,
      "change_pct": -0.16,
      "currency": "USD",
      "found": true
    },
    {
      "id": "JD",
      "name": "징둥ADR",
      "ex": "NASDAQ",
      "sector": "전자상거래",
      "type": "us_adr",
      "price": 29.0,
      "prev_close": 28.66,
      "change_pct": 1.2,
      "currency": "USD",
      "found": true
    },
    {
      "id": "BIDU",
      "name": "바이두",
      "ex": "NASDAQ",
      "sector": "IT",
      "type": "us_adr",
      "price": 120.4,
      "prev_close": 118.68,
      "change_pct": 1.46,
      "currency": "USD",
      "found": true
    },
    {
      "id": "NIO",
      "name": "니오",
      "ex": "NYSE",
      "sector": "EV",
      "type": "us_adr",
      "price": 5.4,
      "prev_close": 5.45,
      "change_pct": -0.92,
      "currency": "USD",
      "found": true
    },
    {
      "id": "LI",
      "name": "리오토",
      "ex": "NASDAQ",
      "sector": "EV",
      "type": "us_adr",
      "price": 14.23,
      "prev_close": 14.5,
      "change_pct": -1.83,
      "currency": "USD",
      "found": true
    },
    {
      "id": "XPEV",
      "name": "샤오펑",
      "ex": "NYSE",
      "sector": "EV",
      "type": "us_adr",
      "price": 15.57,
      "prev_close": 15.87,
      "change_pct": -1.89,
      "currency": "USD",
      "found": true
    },
    {
      "id": "TME",
      "name": "텐센트뮤직",
      "ex": "NYSE",
      "sector": "엔터",
      "type": "us_adr",
      "price": 9.1,
      "prev_close": 9.13,
      "change_pct": -0.38,
      "currency": "USD",
      "found": true
    },
    {
      "id": "BILI",
      "name": "빌리빌리",
      "ex": "NASDAQ",
      "sector": "엔터",
      "type": "us_adr",
      "price": 17.62,
      "prev_close": 18.0,
      "change_pct": -2.11,
      "currency": "USD",
      "found": true
    },
    {
      "id": "NTES",
      "name": "넷이즈",
      "ex": "NASDAQ",
      "sector": "게임",
      "type": "us_adr",
      "price": 119.67,
      "prev_close": 118.82,
      "change_pct": 0.72,
      "currency": "USD",
      "found": true
    },
    {
      "id": "005930",
      "name": "삼성전자",
      "ex": "KOSPI",
      "sector": "반도체",
      "type": "kr_stock",
      "price": 322000.0,
      "prev_close": 295500.0,
      "change_pct": 8.97,
      "currency": "KRW",
      "found": true
    },
    {
      "id": "000660",
      "name": "SK하이닉스",
      "ex": "KOSPI",
      "sector": "반도체",
      "type": "kr_stock",
      "price": 2215000.0,
      "prev_close": 1911000.0,
      "change_pct": 15.91,
      "currency": "KRW",
      "found": true
    },
    {
      "id": "373220",
      "name": "LG에너지솔루션",
      "ex": "KOSPI",
      "sector": "배터리",
      "type": "kr_stock",
      "price": 396500.0,
      "prev_close": 388500.0,
      "change_pct": 2.06,
      "currency": "KRW",
      "found": true
    },
    {
      "id": "005380",
      "name": "현대차",
      "ex": "KOSPI",
      "sector": "자동차",
      "type": "kr_stock",
      "price": 639000.0,
      "prev_close": 639000.0,
      "change_pct": 0.0,
      "currency": "KRW",
      "found": true
    },
    {
      "id": "207940",
      "name": "삼성바이오로직스",
      "ex": "KOSPI",
      "sector": "바이오",
      "type": "kr_stock",
      "price": 1296000.0,
      "prev_close": 1243000.0,
      "change_pct": 4.26,
      "currency": "KRW",
      "found": true
    },
    {
      "id": "035420",
      "name": "NAVER",
      "ex": "KOSPI",
      "sector": "IT",
      "type": "kr_stock",
      "price": 257000.0,
      "prev_close": 279000.0,
      "change_pct": -7.89,
      "currency": "KRW",
      "found": true
    },
    {
      "id": "005490",
      "name": "POSCO홀딩스",
      "ex": "KOSPI",
      "sector": "철강",
      "type": "kr_stock",
      "price": 364500.0,
      "prev_close": 359000.0,
      "change_pct": 1.53,
      "currency": "KRW",
      "found": true
    },
    {
      "id": "051910",
      "name": "LG화학",
      "ex": "KOSPI",
      "sector": "화학",
      "type": "kr_stock",
      "price": 329000.0,
      "prev_close": 321000.0,
      "change_pct": 2.49,
      "currency": "KRW",
      "found": true
    },
    {
      "id": "006400",
      "name": "삼성SDI",
      "ex": "KOSPI",
      "sector": "배터리",
      "type": "kr_stock",
      "price": 515000.0,
      "prev_close": 503000.0,
      "change_pct": 2.39,
      "currency": "KRW",
      "found": true
    },
    {
      "id": "035720",
      "name": "카카오",
      "ex": "KOSPI",
      "sector": "IT",
      "type": "kr_stock",
      "price": 39500.0,
      "prev_close": 38600.0,
      "change_pct": 2.33,
      "currency": "KRW",
      "found": true
    },
    {
      "id": "068270",
      "name": "셀트리온",
      "ex": "KOSPI",
      "sector": "바이오",
      "type": "kr_stock",
      "price": 170000.0,
      "prev_close": 159400.0,
      "change_pct": 6.65,
      "currency": "KRW",
      "found": true
    },
    {
      "id": "105560",
      "name": "KB금융",
      "ex": "KOSPI",
      "sector": "금융",
      "type": "kr_stock",
      "price": 154800.0,
      "prev_close": 151500.0,
      "change_pct": 2.18,
      "currency": "KRW",
      "found": true
    },
    {
      "id": "055550",
      "name": "신한지주",
      "ex": "KOSPI",
      "sector": "금융",
      "type": "kr_stock",
      "price": 101200.0,
      "prev_close": 97100.0,
      "change_pct": 4.22,
      "currency": "KRW",
      "found": true
    },
    {
      "id": "012330",
      "name": "현대모비스",
      "ex": "KOSPI",
      "sector": "자동차",
      "type": "kr_stock",
      "price": 595000.0,
      "prev_close": 612000.0,
      "change_pct": -2.78,
      "currency": "KRW",
      "found": true
    },
    {
      "id": "000270",
      "name": "기아",
      "ex": "KOSPI",
      "sector": "자동차",
      "type": "kr_stock",
      "price": 164300.0,
      "prev_close": 151400.0,
      "change_pct": 8.52,
      "currency": "KRW",
      "found": true
    }
  ],
  "indices": [
    {
      "id": "csi300",
      "name": "CSI 300",
      "type": "index",
      "price": 4801.81,
      "prev_close": 4712.5,
      "change_pct": 1.9,
      "found": true
    },
    {
      "id": "sse",
      "name": "SSE COMP",
      "type": "index",
      "price": 4010.03,
      "prev_close": 3958.98,
      "change_pct": 1.29,
      "found": true
    },
    {
      "id": "szse",
      "name": "SZSE COMP",
      "type": "index",
      "price": 15268.71,
      "prev_close": 14814.58,
      "change_pct": 3.07,
      "found": true
    },
    {
      "id": "hsi",
      "name": "HSI 항셍",
      "type": "index",
      "price": 24565.9,
      "prev_close": 24657.06,
      "change_pct": -0.37,
      "found": true
    },
    {
      "id": "hscei",
      "name": "HSCEI",
      "type": "index",
      "price": 8324.59,
      "prev_close": 8341.36,
      "change_pct": -0.2,
      "found": true
    },
    {
      "id": "kospi",
      "name": "KOSPI",
      "type": "index",
      "price": 8096.93,
      "prev_close": 7484.41,
      "change_pct": 8.18,
      "found": true
    },
    {
      "id": "kosdaq",
      "name": "KOSDAQ",
      "type": "index",
      "price": 967.81,
      "prev_close": 911.39,
      "change_pct": 6.19,
      "found": true
    }
  ],
  "errors": []
}